{
  "/admin/home": {
    "url": "http://177.234.239.116:8084/admin/home",
    "title": "Dashboard",
    "buttons": [],
    "inputs": [],
    "tables": [],
    "artifacts": {
      "screenshot": "data/raw/screenshots/admin_home_20260523_130624.png",
      "html": "data/raw/html/admin_home_20260523_130624.html"
    }
  },
  "/admin/permisos/solicitudes": {
    "url": "http://177.234.239.116:8084/admin/permisos/solicitudes",
    "title": "Dashboard",
    "buttons": [],
    "inputs": [],
    "tables": [
      {
        "headers": [
          "",
          "CÓDIGO",
          "FECHA REGISTRO",
          "SOLICITUD",
          "IDENTIFICACIÓN",
          "SOLICITANTE",
          "RESPONSABLE"
        ],
        "rows_count": 7
      }
    ],
    "artifacts": {
      "screenshot": "data/raw/screenshots/admin_permisos_solicitudes_20260523_130627.png",
      "html": "data/raw/html/admin_permisos_solicitudes_20260523_130627.html"
    }
  },
  "/admin/permisos/emitir": {
    "url": "http://177.234.239.116:8084/admin/permisos/emitir",
    "title": "Dashboard",
    "buttons": [
      "Emitir solicitud",
      "Ver detalle"
    ],
    "inputs": [
      {
        "id": "mat-mdc-checkbox-1-input",
        "name": null,
        "placeholder": null,
        "type": "checkbox"
      }
    ],
    "tables": [
      {
        "headers": [
          "",
          "CÓDIGO",
          "CONCEPTO",
          "AÑO",
          "IDENTIFICACIÓN",
          "SOLICITANTE",
          "F. REGISTRO",
          "F. EMISION",
          "F. VENCE",
          "TOTAL"
        ],
        "rows_count": 1
      }
    ],
    "artifacts": {
      "screenshot": "data/raw/screenshots/admin_permisos_emitir_20260523_130629.png",
      "html": "data/raw/html/admin_permisos_emitir_20260523_130629.html"
    }
  },
  "/admin/permisos/enviar-inspecciones": {
    "url": "http://177.234.239.116:8084/admin/permisos/enviar-inspecciones",
    "title": "Dashboard",
    "buttons": [],
    "inputs": [],
    "tables": [
      {
        "headers": [
          "CÓDIGO",
          "RUC",
          "PROPIETARIO",
          "NOMBRE COMERCIAL",
          "ESTABLECIMIENTO",
          "ZONA",
          "ÁREA COMERCIAL (M²)",
          "CATEGORÍA",
          "NIVEL DE RIESGO",
          "ENVIAR CORREO"
        ],
        "rows_count": 42
      }
    ],
    "artifacts": {
      "screenshot": "data/raw/screenshots/admin_permisos_enviar_inspecciones_20260523_130632.png",
      "html": "data/raw/html/admin_permisos_enviar_inspecciones_20260523_130632.html"
    }
  },
  "/admin/permisos/funcionamiento": {
    "url": "http://177.234.239.116:8084/admin/permisos/funcionamiento",
    "title": "Dashboard",
    "buttons": [
      "Natural",
      "Juridica",
      "Buscar",
      "Reporte diario"
    ],
    "inputs": [
      {
        "id": "mat-input-0",
        "name": null,
        "placeholder": "Número cedula",
        "type": "number"
      }
    ],
    "tables": [],
    "artifacts": {
      "screenshot": "data/raw/screenshots/admin_permisos_funcionamiento_20260523_130635.png",
      "html": "data/raw/html/admin_permisos_funcionamiento_20260523_130635.html"
    }
  },
  "/admin/permisos/inspecciones": {
    "url": "http://177.234.239.116:8084/admin/permisos/inspecciones",
    "title": "Dashboard",
    "buttons": [
      "Buscar",
      "Limpiar",
      "Imprimir"
    ],
    "inputs": [],
    "tables": [
      {
        "headers": [
          "CÓDIGO",
          "FECHA",
          "HORA",
          "RUC",
          "PROPIETARIO",
          "NOMBRE COMERCIAL",
          "ESTAB.",
          "DIRECCION",
          "ZONA"
        ],
        "rows_count": 11
      }
    ],
    "artifacts": {
      "screenshot": "data/raw/screenshots/admin_permisos_inspecciones_20260523_130638.png",
      "html": "data/raw/html/admin_permisos_inspecciones_20260523_130638.html"
    }
  }
}